{
  "metadata": {
    "source": "Statistics Finland",
    "table": "statfin_mata_pxt_12gf",
    "description": "Current account and balance of payments",
    "fetched_at": "2026-01-03T22:43:42.528676",
    "unit": "Million EUR"
  },
  "summary": {
    "period": "2006-2025",
    "current_balance_billion": 2.05,
    "peak_year": 2007,
    "peak_balance_billion": 8.97,
    "surplus_years": 12,
    "deficit_years": 8,
    "services_share_change": 18.98,
    "key_insight": "Finland went from €7.2B balance in 2006 to €2.0B in 2025"
  },
  "time_series": [
    {
      "year": 2006,
      "exports_total": 74471,
      "imports_total": 67270,
      "trade_balance": 7201,
      "goods_balance": 13113,
      "services_balance": -5912,
      "goods_exports": 64993,
      "goods_imports": 51880,
      "services_exports": 9478,
      "services_imports": 15390,
      "current_account": 6797,
      "export_coverage_pct": 110.7,
      "services_share_pct": 12.73
    },
    {
      "year": 2007,
      "exports_total": 81990,
      "imports_total": 73015,
      "trade_balance": 8975,
      "goods_balance": 15759,
      "services_balance": -6784,
      "goods_exports": 71715,
      "goods_imports": 55956,
      "services_exports": 10275,
      "services_imports": 17059,
      "current_account": 7535,
      "export_coverage_pct": 112.29,
      "services_share_pct": 12.53
    },
    {
      "year": 2008,
      "exports_total": 87224,
      "imports_total": 80198,
      "trade_balance": 7026,
      "goods_balance": 12961,
      "services_balance": -5935,
      "goods_exports": 71310,
      "goods_imports": 58349,
      "services_exports": 15914,
      "services_imports": 21849,
      "current_account": 4940,
      "export_coverage_pct": 108.76,
      "services_share_pct": 18.24
    },
    {
      "year": 2009,
      "exports_total": 65577,
      "imports_total": 61870,
      "trade_balance": 3707,
      "goods_balance": 9595,
      "services_balance": -5888,
      "goods_exports": 51258,
      "goods_imports": 41663,
      "services_exports": 14319,
      "services_imports": 20207,
      "current_account": 3627,
      "export_coverage_pct": 105.99,
      "services_share_pct": 21.84
    },
    {
      "year": 2010,
      "exports_total": 72275,
      "imports_total": 69707,
      "trade_balance": 2568,
      "goods_balance": 7434,
      "services_balance": -4866,
      "goods_exports": 56516,
      "goods_imports": 49082,
      "services_exports": 15759,
      "services_imports": 20625,
      "current_account": 2562,
      "export_coverage_pct": 103.68,
      "services_share_pct": 21.8
    },
    {
      "year": 2011,
      "exports_total": 77022,
      "imports_total": 78568,
      "trade_balance": -1546,
      "goods_balance": 2305,
      "services_balance": -3851,
      "goods_exports": 59370,
      "goods_imports": 57065,
      "services_exports": 17652,
      "services_imports": 21503,
      "current_account": -3067,
      "export_coverage_pct": 98.03,
      "services_share_pct": 22.92
    },
    {
      "year": 2012,
      "exports_total": 78017,
      "imports_total": 81144,
      "trade_balance": -3127,
      "goods_balance": 2419,
      "services_balance": -5546,
      "goods_exports": 59482,
      "goods_imports": 57063,
      "services_exports": 18535,
      "services_imports": 24081,
      "current_account": -4469,
      "export_coverage_pct": 96.15,
      "services_share_pct": 23.76
    },
    {
      "year": 2013,
      "exports_total": 77836,
      "imports_total": 79840,
      "trade_balance": -2004,
      "goods_balance": 2353,
      "services_balance": -4357,
      "goods_exports": 58586,
      "goods_imports": 56233,
      "services_exports": 19250,
      "services_imports": 23607,
      "current_account": -3831,
      "export_coverage_pct": 97.49,
      "services_share_pct": 24.73
    },
    {
      "year": 2014,
      "exports_total": 75768,
      "imports_total": 77858,
      "trade_balance": -2090,
      "goods_balance": 1414,
      "services_balance": -3504,
      "goods_exports": 56061,
      "goods_imports": 54647,
      "services_exports": 19707,
      "services_imports": 23211,
      "current_account": -2793,
      "export_coverage_pct": 97.32,
      "services_share_pct": 26.01
    },
    {
      "year": 2015,
      "exports_total": 75215,
      "imports_total": 76046,
      "trade_balance": -831,
      "goods_balance": 1912,
      "services_balance": -2743,
      "goods_exports": 53015,
      "goods_imports": 51103,
      "services_exports": 22200,
      "services_imports": 24943,
      "current_account": -1908,
      "export_coverage_pct": 98.91,
      "services_share_pct": 29.52
    },
    {
      "year": 2016,
      "exports_total": 76218,
      "imports_total": 78496,
      "trade_balance": -2278,
      "goods_balance": 23,
      "services_balance": -2301,
      "goods_exports": 52721,
      "goods_imports": 52698,
      "services_exports": 23497,
      "services_imports": 25798,
      "current_account": -4253,
      "export_coverage_pct": 97.1,
      "services_share_pct": 30.83
    },
    {
      "year": 2017,
      "exports_total": 85760,
      "imports_total": 84875,
      "trade_balance": 885,
      "goods_balance": 1652,
      "services_balance": -767,
      "goods_exports": 59455,
      "goods_imports": 57803,
      "services_exports": 26305,
      "services_imports": 27072,
      "current_account": -1472,
      "export_coverage_pct": 101.04,
      "services_share_pct": 30.67
    },
    {
      "year": 2018,
      "exports_total": 90789,
      "imports_total": 92749,
      "trade_balance": -1960,
      "goods_balance": 434,
      "services_balance": -2394,
      "goods_exports": 62926,
      "goods_imports": 62492,
      "services_exports": 27863,
      "services_imports": 30257,
      "current_account": -3736,
      "export_coverage_pct": 97.89,
      "services_share_pct": 30.69
    },
    {
      "year": 2019,
      "exports_total": 96879,
      "imports_total": 95276,
      "trade_balance": 1603,
      "goods_balance": 2499,
      "services_balance": -896,
      "goods_exports": 64925,
      "goods_imports": 62426,
      "services_exports": 31954,
      "services_imports": 32850,
      "current_account": -329,
      "export_coverage_pct": 101.68,
      "services_share_pct": 32.98
    },
    {
      "year": 2020,
      "exports_total": 85608,
      "imports_total": 85028,
      "trade_balance": 580,
      "goods_balance": 2917,
      "services_balance": -2337,
      "goods_exports": 58958,
      "goods_imports": 56041,
      "services_exports": 26650,
      "services_imports": 28987,
      "current_account": 1002,
      "export_coverage_pct": 100.68,
      "services_share_pct": 31.13
    },
    {
      "year": 2021,
      "exports_total": 99309,
      "imports_total": 99175,
      "trade_balance": 134,
      "goods_balance": 2195,
      "services_balance": -2061,
      "goods_exports": 70234,
      "goods_imports": 68039,
      "services_exports": 29075,
      "services_imports": 31136,
      "current_account": 821,
      "export_coverage_pct": 100.14,
      "services_share_pct": 29.28
    },
    {
      "year": 2022,
      "exports_total": 123181,
      "imports_total": 128483,
      "trade_balance": -5302,
      "goods_balance": -232,
      "services_balance": -5070,
      "goods_exports": 88859,
      "goods_imports": 89091,
      "services_exports": 34322,
      "services_imports": 39392,
      "current_account": -6430,
      "export_coverage_pct": 95.87,
      "services_share_pct": 27.86
    },
    {
      "year": 2023,
      "exports_total": 116760,
      "imports_total": 116703,
      "trade_balance": 57,
      "goods_balance": 8177,
      "services_balance": -8120,
      "goods_exports": 82638,
      "goods_imports": 74461,
      "services_exports": 34122,
      "services_imports": 42242,
      "current_account": -2503,
      "export_coverage_pct": 100.05,
      "services_share_pct": 29.22
    },
    {
      "year": 2024,
      "exports_total": 115651,
      "imports_total": 114669,
      "trade_balance": 982,
      "goods_balance": 6000,
      "services_balance": -5018,
      "goods_exports": 76823,
      "goods_imports": 70823,
      "services_exports": 38828,
      "services_imports": 43846,
      "current_account": -1219,
      "export_coverage_pct": 100.86,
      "services_share_pct": 33.57
    },
    {
      "year": 2025,
      "exports_total": 97538,
      "imports_total": 95490,
      "trade_balance": 2048,
      "goods_balance": 6922,
      "services_balance": -4874,
      "goods_exports": 66607,
      "goods_imports": 59685,
      "services_exports": 30931,
      "services_imports": 35805,
      "current_account": 1593,
      "export_coverage_pct": 102.14,
      "services_share_pct": 31.71
    }
  ]
}